nnlogging/__init__.py
nnlogging/global_.py
nnlogging/shell.py
nnlogging/exceptions/__init__.py
nnlogging/exceptions/branch_exists.py
nnlogging/exceptions/branch_not_found.py
nnlogging/exceptions/task_exists.py
nnlogging/exceptions/task_not_found.py
nnlogging/options/__init__.py
nnlogging/options/branch_config.py
nnlogging/options/log_option.py
nnlogging/options/logger_config.py
nnlogging/options/rich_console.py
nnlogging/options/rich_handler.py
nnlogging/options/rich_progress.py
nnlogging/options/run_config.py
nnlogging/options/task_option.py
nnlogging/options/track_option.py
nnlogging/shell_funcs/__init__.py
nnlogging/shell_funcs/branch_.py
nnlogging/shell_funcs/logger_.py
nnlogging/shell_funcs/run_.py
nnlogging/shell_funcs/task_.py
nnlogging/typings/aliases.py
nnlogging/typings/exts.py
nnlogging/typings/protocols.py
nnlogging/utils/factories.py
nnlogging/utils/helpers.py
nnlogging-0.1.4.dist-info/METADATA
nnlogging-0.1.4.dist-info/WHEEL
nnlogging-0.1.4.dist-info/RECORD
