Metadata-Version: 2.4
Name: nnlogging
Version: 0.1.4
Summary: A powerful and elegant logging library designed specifically for neural network and machine learning experiments. nnlogging seamlessly integrates [Rich](https://github.com/Textualize/rich) for beautiful terminal output and [Aim](https://github.com/aimhubio/aim) for comprehensive experiment tracking.
Requires-Python: <3.13,>=3.10
Requires-Dist: aim>=3.29.0
Requires-Dist: rich>=14.0.0
Provides-Extra: dev
Requires-Dist: faker>=37.11.0; extra == 'dev'
Requires-Dist: pytest-cov>=7.0.0; extra == 'dev'
Requires-Dist: pytest-html>=4.1.1; extra == 'dev'
Requires-Dist: pytest-repeat>=0.9.4; extra == 'dev'
Requires-Dist: pytest-sugar>=1.1.1; extra == 'dev'
Requires-Dist: pytest-xdist>=3.8.0; extra == 'dev'
Requires-Dist: pytest>=8.4.2; extra == 'dev'
Requires-Dist: twine>=6.2.0; extra == 'dev'
